infi.sgutils-0.1.14-py2.7-nspkg.pth
infi/sgutils/__init__.py
infi/sgutils/__version__.py
infi/sgutils/ioctl/__init__.py
infi/sgutils/ioctl/opcodes/__init__.py
infi/sgutils/ioctl/structures/__init__.py
infi/sgutils/ioctl/tests/__init__.py
infi/sgutils/sg_map/__init__.py
infi/sgutils/sg_map/tests/__init__.py
infi/sgutils/sg_reset/__init__.py
infi.sgutils-0.1.14.dist-info/LICENSE
infi.sgutils-0.1.14.dist-info/METADATA
infi.sgutils-0.1.14.dist-info/WHEEL
infi.sgutils-0.1.14.dist-info/entry_points.txt
infi.sgutils-0.1.14.dist-info/namespace_packages.txt
infi.sgutils-0.1.14.dist-info/top_level.txt
infi.sgutils-0.1.14.dist-info/RECORD
