Metadata-Version: 2.1
Name: infi.sgutils
Version: 0.1.14
Summary: an attempt to be a pure-Python implementation of sg3-utils
Home-page: https://github.com/Infinidat/infi.sgutils
Author: Arnon Yaari
Author-email: arnony@infinidat.com
License: BSD
Platform: UNKNOWN
Classifier: Intended Audience :: Developers
Classifier: Intended Audience :: System Administrators
Classifier: License :: OSI Approved :: BSD License
Classifier: Operating System :: OS Independent
Classifier: Programming Language :: Python
Classifier: Programming Language :: Python :: 2
Classifier: Programming Language :: Python :: 3
Classifier: Topic :: Software Development :: Libraries :: Python Modules
Requires-Dist: infi.dtypes.hctl
Requires-Dist: infi.instruct
Requires-Dist: setuptools
